{"Net_assets_share_type":{"Net_assets_share_type":1.0,"Numbre_of_Shares_outstanding":0.6975246272,"NAV_share":0.9495389491,"NUMBER_unit_subsc":0.0349336844,"Amount_subsc":0.0532884972,"NUMBER_unit_repurch":-0.0018561516,"Amount_unit_repurch":0.0048266872,"Dividend_share":null,"Date_pay_div":null,"Pccy_dividend_share":null,"Total_Net_Assets":1.0},"Numbre_of_Shares_outstanding":{"Net_assets_share_type":0.6975246272,"Numbre_of_Shares_outstanding":1.0,"NAV_share":0.4379221224,"NUMBER_unit_subsc":-0.0688921077,"Amount_subsc":-0.0534786924,"NUMBER_unit_repurch":0.0759144223,"Amount_unit_repurch":0.0790466898,"Dividend_share":null,"Date_pay_div":null,"Pccy_dividend_share":null,"Total_Net_Assets":0.6975246272},"NAV_share":{"Net_assets_share_type":0.9495389491,"Numbre_of_Shares_outstanding":0.4379221224,"NAV_share":1.0,"NUMBER_unit_subsc":0.070990531,"Amount_subsc":0.0872501597,"NUMBER_unit_repurch":-0.035729258,"Amount_unit_repurch":-0.0287466998,"Dividend_share":null,"Date_pay_div":null,"Pccy_dividend_share":null,"Total_Net_Assets":0.9495389491},"NUMBER_unit_subsc":{"Net_assets_share_type":0.0349336844,"Numbre_of_Shares_outstanding":-0.0688921077,"NAV_share":0.070990531,"NUMBER_unit_subsc":1.0,"Amount_subsc":0.9988060042,"NUMBER_unit_repurch":-0.0509917045,"Amount_unit_repurch":-0.0516073862,"Dividend_share":null,"Date_pay_div":null,"Pccy_dividend_share":null,"Total_Net_Assets":0.0349336844},"Amount_subsc":{"Net_assets_share_type":0.0532884972,"Numbre_of_Shares_outstanding":-0.0534786924,"NAV_share":0.0872501597,"NUMBER_unit_subsc":0.9988060042,"Amount_subsc":1.0,"NUMBER_unit_repurch":-0.0499810838,"Amount_unit_repurch":-0.050532488,"Dividend_share":null,"Date_pay_div":null,"Pccy_dividend_share":null,"Total_Net_Assets":0.0532884972},"NUMBER_unit_repurch":{"Net_assets_share_type":-0.0018561516,"Numbre_of_Shares_outstanding":0.0759144223,"NAV_share":-0.035729258,"NUMBER_unit_subsc":-0.0509917045,"Amount_subsc":-0.0499810838,"NUMBER_unit_repurch":1.0,"Amount_unit_repurch":0.9998284696,"Dividend_share":null,"Date_pay_div":null,"Pccy_dividend_share":null,"Total_Net_Assets":-0.0018561516},"Amount_unit_repurch":{"Net_assets_share_type":0.0048266872,"Numbre_of_Shares_outstanding":0.0790466898,"NAV_share":-0.0287466998,"NUMBER_unit_subsc":-0.0516073862,"Amount_subsc":-0.050532488,"NUMBER_unit_repurch":0.9998284696,"Amount_unit_repurch":1.0,"Dividend_share":null,"Date_pay_div":null,"Pccy_dividend_share":null,"Total_Net_Assets":0.0048266872},"Dividend_share":{"Net_assets_share_type":null,"Numbre_of_Shares_outstanding":null,"NAV_share":null,"NUMBER_unit_subsc":null,"Amount_subsc":null,"NUMBER_unit_repurch":null,"Amount_unit_repurch":null,"Dividend_share":null,"Date_pay_div":null,"Pccy_dividend_share":null,"Total_Net_Assets":null},"Date_pay_div":{"Net_assets_share_type":null,"Numbre_of_Shares_outstanding":null,"NAV_share":null,"NUMBER_unit_subsc":null,"Amount_subsc":null,"NUMBER_unit_repurch":null,"Amount_unit_repurch":null,"Dividend_share":null,"Date_pay_div":null,"Pccy_dividend_share":null,"Total_Net_Assets":null},"Pccy_dividend_share":{"Net_assets_share_type":null,"Numbre_of_Shares_outstanding":null,"NAV_share":null,"NUMBER_unit_subsc":null,"Amount_subsc":null,"NUMBER_unit_repurch":null,"Amount_unit_repurch":null,"Dividend_share":null,"Date_pay_div":null,"Pccy_dividend_share":null,"Total_Net_Assets":null},"Total_Net_Assets":{"Net_assets_share_type":1.0,"Numbre_of_Shares_outstanding":0.6975246272,"NAV_share":0.9495389491,"NUMBER_unit_subsc":0.0349336844,"Amount_subsc":0.0532884972,"NUMBER_unit_repurch":-0.0018561516,"Amount_unit_repurch":0.0048266872,"Dividend_share":null,"Date_pay_div":null,"Pccy_dividend_share":null,"Total_Net_Assets":1.0}}